{"schema_version":"web/v1","surface":"polling_places","partition":{"year":2024,"state":"RO","round":1,"city_id":"00353","page":1},"generated_at_utc":"2026-06-12T15:33:51.206681+00:00","source_type":"consolidado_tse","row_count":34,"rows":[{"id":"819b2a0ef144751a6a4a458778b5c23e2dd4e2ab6c3b85ceb310e162a4a317ed","year":2024,"round":1,"state":"RO","city_id":"00353","city_name":"SANTA LUZIA D'OESTE","zone_id":"19","section_id":"1","polling_place_id":"1082","polling_place_name":"JUSCELINO KUBITSCHEK - ESCOLA ESTADUAL - 1 E 2 GRAU","section_voters":214,"latitude":null,"longitude":null,"geocoding_note":"Sem geocodificacao externa nesta etapa; latitude/longitude permanecem sem dado."},{"id":"0efbab11e499c872ca44d25d59aa7d59d0bb83fd8ac9bbab6fb49d6ea040741e","year":2024,"round":1,"state":"RO","city_id":"00353","city_name":"SANTA LUZIA D'OESTE","zone_id":"19","section_id":"10","polling_place_id":"1082","polling_place_name":"JUSCELINO KUBITSCHEK - ESCOLA ESTADUAL - 1 E 2 GRAU","section_voters":211,"latitude":null,"longitude":null,"geocoding_note":"Sem geocodificacao externa nesta etapa; latitude/longitude permanecem sem dado."},{"id":"9c0c3430a3b70872d4b58060e31ca09792397f7e1a15f9c825305e081636423f","year":2024,"round":1,"state":"RO","city_id":"00353","city_name":"SANTA LUZIA D'OESTE","zone_id":"19","section_id":"11","polling_place_id":"1082","polling_place_name":"JUSCELINO KUBITSCHEK - ESCOLA ESTADUAL - 1 E 2 GRAU","section_voters":212,"latitude":null,"longitude":null,"geocoding_note":"Sem geocodificacao externa nesta etapa; latitude/longitude permanecem sem dado."},{"id":"5f9c3fded6088013be0d5c63e0bff7d29e774b2f3c96a35afd6ccedbbe22c212","year":2024,"round":1,"state":"RO","city_id":"00353","city_name":"SANTA LUZIA D'OESTE","zone_id":"19","section_id":"12","polling_place_id":"1082","polling_place_name":"JUSCELINO KUBITSCHEK - ESCOLA ESTADUAL - 1 E 2 GRAU","section_voters":215,"latitude":null,"longitude":null,"geocoding_note":"Sem geocodificacao externa nesta etapa; latitude/longitude permanecem sem dado."},{"id":"abf86f7fddd9e4a5eb6e580ca09bce7ef412ce1a93a99783cfc6ec8dbe4b4c1b","year":2024,"round":1,"state":"RO","city_id":"00353","city_name":"SANTA LUZIA D'OESTE","zone_id":"19","section_id":"123","polling_place_id":"1287","polling_place_name":"JOSÉ RONALDO ARAGÃO - ESCOLA MUNICIPAL","section_voters":161,"latitude":null,"longitude":null,"geocoding_note":"Sem geocodificacao externa nesta etapa; latitude/longitude permanecem sem dado."},{"id":"671ceef6903301c67814c7036999b7d62558dbbcd771754c16059ff0d7d8af88","year":2024,"round":1,"state":"RO","city_id":"00353","city_name":"SANTA LUZIA D'OESTE","zone_id":"19","section_id":"124","polling_place_id":"1287","polling_place_name":"JOSÉ RONALDO ARAGÃO - ESCOLA MUNICIPAL","section_voters":158,"latitude":null,"longitude":null,"geocoding_note":"Sem geocodificacao externa nesta etapa; latitude/longitude permanecem sem dado."},{"id":"a5477ad1e18bc18439494cf5a953131201b32a3d85d4ac2cc52a1a334e4e32f0","year":2024,"round":1,"state":"RO","city_id":"00353","city_name":"SANTA LUZIA D'OESTE","zone_id":"19","section_id":"13","polling_place_id":"1082","polling_place_name":"JUSCELINO KUBITSCHEK - ESCOLA ESTADUAL - 1 E 2 GRAU","section_voters":210,"latitude":null,"longitude":null,"geocoding_note":"Sem geocodificacao externa nesta etapa; latitude/longitude permanecem sem dado."},{"id":"2a1c07e916827b53825d56e1a70978ccd3a2f5b09a1ce79f5e39875df7f5770b","year":2024,"round":1,"state":"RO","city_id":"00353","city_name":"SANTA LUZIA D'OESTE","zone_id":"19","section_id":"138","polling_place_id":"1333","polling_place_name":"MANOEL DE LIMA PAZ - ESCOLA MUNICIPAL","section_voters":308,"latitude":null,"longitude":null,"geocoding_note":"Sem geocodificacao externa nesta etapa; latitude/longitude permanecem sem dado."},{"id":"49088a9bef0ea5bf73f182c529608f0abac97d420dda196c0c29f8ac7e3e5bff","year":2024,"round":1,"state":"RO","city_id":"00353","city_name":"SANTA LUZIA D'OESTE","zone_id":"19","section_id":"14","polling_place_id":"1287","polling_place_name":"JOSÉ RONALDO ARAGÃO - ESCOLA MUNICIPAL","section_voters":161,"latitude":null,"longitude":null,"geocoding_note":"Sem geocodificacao externa nesta etapa; latitude/longitude permanecem sem dado."},{"id":"d6afcb2d9f7a4ca30f7cff9a0ce66f59b9ad76502da8f859ac4ae9aab6757321","year":2024,"round":1,"state":"RO","city_id":"00353","city_name":"SANTA LUZIA D'OESTE","zone_id":"19","section_id":"16","polling_place_id":"1287","polling_place_name":"JOSÉ RONALDO ARAGÃO - ESCOLA MUNICIPAL","section_voters":163,"latitude":null,"longitude":null,"geocoding_note":"Sem geocodificacao externa nesta etapa; latitude/longitude permanecem sem dado."},{"id":"97a27b0eee6fc123682bd1d9d61596e144876d5695c8d6346fad34c5bc9b013c","year":2024,"round":1,"state":"RO","city_id":"00353","city_name":"SANTA LUZIA D'OESTE","zone_id":"19","section_id":"18","polling_place_id":"1287","polling_place_name":"JOSÉ RONALDO ARAGÃO - ESCOLA MUNICIPAL","section_voters":163,"latitude":null,"longitude":null,"geocoding_note":"Sem geocodificacao externa nesta etapa; latitude/longitude permanecem sem dado."},{"id":"8d3f8734b01e2763cfe9171cb950505b253f93aa412665df0f81621b8c0b2fb8","year":2024,"round":1,"state":"RO","city_id":"00353","city_name":"SANTA LUZIA D'OESTE","zone_id":"19","section_id":"2","polling_place_id":"1082","polling_place_name":"JUSCELINO KUBITSCHEK - ESCOLA ESTADUAL - 1 E 2 GRAU","section_voters":216,"latitude":null,"longitude":null,"geocoding_note":"Sem geocodificacao externa nesta etapa; latitude/longitude permanecem sem dado."},{"id":"6474be9fa2e523cf898e469444cff0e8a221ee42cd123c9b9097d81bb9ed074e","year":2024,"round":1,"state":"RO","city_id":"00353","city_name":"SANTA LUZIA D'OESTE","zone_id":"19","section_id":"20","polling_place_id":"1287","polling_place_name":"JOSÉ RONALDO ARAGÃO - ESCOLA MUNICIPAL","section_voters":161,"latitude":null,"longitude":null,"geocoding_note":"Sem geocodificacao externa nesta etapa; latitude/longitude permanecem sem dado."},{"id":"38f422d1d467063d08276c866656c564fe174cf5b200ffe645cd7fe529a60353","year":2024,"round":1,"state":"RO","city_id":"00353","city_name":"SANTA LUZIA D'OESTE","zone_id":"19","section_id":"22","polling_place_id":"1287","polling_place_name":"JOSÉ RONALDO ARAGÃO - ESCOLA MUNICIPAL","section_voters":163,"latitude":null,"longitude":null,"geocoding_note":"Sem geocodificacao externa nesta etapa; latitude/longitude permanecem sem dado."},{"id":"a86fe3c18a66e23f12cf5d76af5eade684667db975b60be832025567864ad136","year":2024,"round":1,"state":"RO","city_id":"00353","city_name":"SANTA LUZIA D'OESTE","zone_id":"19","section_id":"24","polling_place_id":"1287","polling_place_name":"JOSÉ RONALDO ARAGÃO - ESCOLA MUNICIPAL","section_voters":163,"latitude":null,"longitude":null,"geocoding_note":"Sem geocodificacao externa nesta etapa; latitude/longitude permanecem sem dado."},{"id":"5328d9d72ef70772143333d231bb3d04efe57cf3fa4605e84394825e4f56e3ed","year":2024,"round":1,"state":"RO","city_id":"00353","city_name":"SANTA LUZIA D'OESTE","zone_id":"19","section_id":"26","polling_place_id":"1287","polling_place_name":"JOSÉ RONALDO ARAGÃO - ESCOLA MUNICIPAL","section_voters":158,"latitude":null,"longitude":null,"geocoding_note":"Sem geocodificacao externa nesta etapa; latitude/longitude permanecem sem dado."},{"id":"5ce4eb29f6c6b8d551b5c9dbbcb986679229f0d7f13b9f6d4ca9a2d5e077ef82","year":2024,"round":1,"state":"RO","city_id":"00353","city_name":"SANTA LUZIA D'OESTE","zone_id":"19","section_id":"28","polling_place_id":"1287","polling_place_name":"JOSÉ RONALDO ARAGÃO - ESCOLA MUNICIPAL","section_voters":155,"latitude":null,"longitude":null,"geocoding_note":"Sem geocodificacao externa nesta etapa; latitude/longitude permanecem sem dado."},{"id":"845894297c3dff63fdcde5a1f91e27c002294849ed3d9469d70bc936348b4ed7","year":2024,"round":1,"state":"RO","city_id":"00353","city_name":"SANTA LUZIA D'OESTE","zone_id":"19","section_id":"3","polling_place_id":"1082","polling_place_name":"JUSCELINO KUBITSCHEK - ESCOLA ESTADUAL - 1 E 2 GRAU","section_voters":209,"latitude":null,"longitude":null,"geocoding_note":"Sem geocodificacao externa nesta etapa; latitude/longitude permanecem sem dado."},{"id":"10868d67bcb88fe493c6734a4bda76f4d9a008ceb0b6340bb8661f29a9f5ca6f","year":2024,"round":1,"state":"RO","city_id":"00353","city_name":"SANTA LUZIA D'OESTE","zone_id":"19","section_id":"30","polling_place_id":"1082","polling_place_name":"JUSCELINO KUBITSCHEK - ESCOLA ESTADUAL - 1 E 2 GRAU","section_voters":214,"latitude":null,"longitude":null,"geocoding_note":"Sem geocodificacao externa nesta etapa; latitude/longitude permanecem sem dado."},{"id":"947c0ef606df2f9969fd2595b13619ccd9c5b9f69c65cc039414a769633d4c0e","year":2024,"round":1,"state":"RO","city_id":"00353","city_name":"SANTA LUZIA D'OESTE","zone_id":"19","section_id":"31","polling_place_id":"1287","polling_place_name":"JOSÉ RONALDO ARAGÃO - ESCOLA MUNICIPAL","section_voters":161,"latitude":null,"longitude":null,"geocoding_note":"Sem geocodificacao externa nesta etapa; latitude/longitude permanecem sem dado."},{"id":"11062626f0e9510a140f65e6f01381c88f5fe66fcea2a8d9382709e4c5f05f0a","year":2024,"round":1,"state":"RO","city_id":"00353","city_name":"SANTA LUZIA D'OESTE","zone_id":"19","section_id":"34","polling_place_id":"1040","polling_place_name":"ASPRUBE - ASSOCIAÇÃO","section_voters":172,"latitude":null,"longitude":null,"geocoding_note":"Sem geocodificacao externa nesta etapa; latitude/longitude permanecem sem dado."},{"id":"b4d68a53a30100bc568f34b938af5506ec0dd85a89784fde99bb61098cf9c425","year":2024,"round":1,"state":"RO","city_id":"00353","city_name":"SANTA LUZIA D'OESTE","zone_id":"19","section_id":"36","polling_place_id":"1333","polling_place_name":"MANOEL DE LIMA PAZ - ESCOLA MUNICIPAL","section_voters":292,"latitude":null,"longitude":null,"geocoding_note":"Sem geocodificacao externa nesta etapa; latitude/longitude permanecem sem dado."},{"id":"149e20aad54c100bec212712e2e7420a3f321f048e2952e8424decd91c81a4bd","year":2024,"round":1,"state":"RO","city_id":"00353","city_name":"SANTA LUZIA D'OESTE","zone_id":"19","section_id":"37","polling_place_id":"1082","polling_place_name":"JUSCELINO KUBITSCHEK - ESCOLA ESTADUAL - 1 E 2 GRAU","section_voters":213,"latitude":null,"longitude":null,"geocoding_note":"Sem geocodificacao externa nesta etapa; latitude/longitude permanecem sem dado."},{"id":"a522e97bba7e4a116f673e585ead86647f61ae6c52103b12b0e9c3897455c51c","year":2024,"round":1,"state":"RO","city_id":"00353","city_name":"SANTA LUZIA D'OESTE","zone_id":"19","section_id":"38","polling_place_id":"1333","polling_place_name":"MANOEL DE LIMA PAZ - ESCOLA MUNICIPAL","section_voters":304,"latitude":null,"longitude":null,"geocoding_note":"Sem geocodificacao externa nesta etapa; latitude/longitude permanecem sem dado."},{"id":"d96d2cfdc7990d7b942e388f07dfa021f62f9c89b9dd0616eff42de04baeee28","year":2024,"round":1,"state":"RO","city_id":"00353","city_name":"SANTA LUZIA D'OESTE","zone_id":"19","section_id":"4","polling_place_id":"1082","polling_place_name":"JUSCELINO KUBITSCHEK - ESCOLA ESTADUAL - 1 E 2 GRAU","section_voters":214,"latitude":null,"longitude":null,"geocoding_note":"Sem geocodificacao externa nesta etapa; latitude/longitude permanecem sem dado."},{"id":"15f5573632c070b627f65edd6b5c801938c562b15adc1d9863699753141077f1","year":2024,"round":1,"state":"RO","city_id":"00353","city_name":"SANTA LUZIA D'OESTE","zone_id":"19","section_id":"5","polling_place_id":"1082","polling_place_name":"JUSCELINO KUBITSCHEK - ESCOLA ESTADUAL - 1 E 2 GRAU","section_voters":212,"latitude":null,"longitude":null,"geocoding_note":"Sem geocodificacao externa nesta etapa; latitude/longitude permanecem sem dado."},{"id":"4624a76700b2308ffccea68510d82bf2091dd1418611acd8dfa9409bdde60cad","year":2024,"round":1,"state":"RO","city_id":"00353","city_name":"SANTA LUZIA D'OESTE","zone_id":"19","section_id":"6","polling_place_id":"1082","polling_place_name":"JUSCELINO KUBITSCHEK - ESCOLA ESTADUAL - 1 E 2 GRAU","section_voters":218,"latitude":null,"longitude":null,"geocoding_note":"Sem geocodificacao externa nesta etapa; latitude/longitude permanecem sem dado."},{"id":"270d441e6b978a9e2d4c05612feacad01cf7896597920f102d1b7093524486ba","year":2024,"round":1,"state":"RO","city_id":"00353","city_name":"SANTA LUZIA D'OESTE","zone_id":"19","section_id":"7","polling_place_id":"1082","polling_place_name":"JUSCELINO KUBITSCHEK - ESCOLA ESTADUAL - 1 E 2 GRAU","section_voters":216,"latitude":null,"longitude":null,"geocoding_note":"Sem geocodificacao externa nesta etapa; latitude/longitude permanecem sem dado."},{"id":"9783a759e6ae968f5dbfc30f3caaf5dc7b6336d67b209127e188946eee8b4cdc","year":2024,"round":1,"state":"RO","city_id":"00353","city_name":"SANTA LUZIA D'OESTE","zone_id":"19","section_id":"8","polling_place_id":"1082","polling_place_name":"JUSCELINO KUBITSCHEK - ESCOLA ESTADUAL - 1 E 2 GRAU","section_voters":214,"latitude":null,"longitude":null,"geocoding_note":"Sem geocodificacao externa nesta etapa; latitude/longitude permanecem sem dado."},{"id":"d3977accb035099b4a3961f5e93538d2fdd90e9b2f1dfdffe7a12b88e4733355","year":2024,"round":1,"state":"RO","city_id":"00353","city_name":"SANTA LUZIA D'OESTE","zone_id":"19","section_id":"84","polling_place_id":"1287","polling_place_name":"JOSÉ RONALDO ARAGÃO - ESCOLA MUNICIPAL","section_voters":160,"latitude":null,"longitude":null,"geocoding_note":"Sem geocodificacao externa nesta etapa; latitude/longitude permanecem sem dado."},{"id":"3c0a217c8278d591be3a290fd144bf04bf6139abaa416bb8edafb6ac9bb026f6","year":2024,"round":1,"state":"RO","city_id":"00353","city_name":"SANTA LUZIA D'OESTE","zone_id":"19","section_id":"85","polling_place_id":"1333","polling_place_name":"MANOEL DE LIMA PAZ - ESCOLA MUNICIPAL","section_voters":300,"latitude":null,"longitude":null,"geocoding_note":"Sem geocodificacao externa nesta etapa; latitude/longitude permanecem sem dado."},{"id":"8abb55f652df52cb7edf6847e57a0aaff668137592da4166dcad9d5c7d1f4267","year":2024,"round":1,"state":"RO","city_id":"00353","city_name":"SANTA LUZIA D'OESTE","zone_id":"19","section_id":"86","polling_place_id":"1090","polling_place_name":"IGREJA SAGRADO CORAÇÃO DE JESUS","section_voters":236,"latitude":null,"longitude":null,"geocoding_note":"Sem geocodificacao externa nesta etapa; latitude/longitude permanecem sem dado."},{"id":"9623e60a858f9ee84183717c2ea54433e0978c2ed9a77a11ac70c59da25237d2","year":2024,"round":1,"state":"RO","city_id":"00353","city_name":"SANTA LUZIA D'OESTE","zone_id":"19","section_id":"87","polling_place_id":"1333","polling_place_name":"MANOEL DE LIMA PAZ - ESCOLA MUNICIPAL","section_voters":300,"latitude":null,"longitude":null,"geocoding_note":"Sem geocodificacao externa nesta etapa; latitude/longitude permanecem sem dado."},{"id":"26676e764343ab2894fb40f663d356a5d9e3713c7bb25438f672747395af9866","year":2024,"round":1,"state":"RO","city_id":"00353","city_name":"SANTA LUZIA D'OESTE","zone_id":"19","section_id":"9","polling_place_id":"1082","polling_place_name":"JUSCELINO KUBITSCHEK - ESCOLA ESTADUAL - 1 E 2 GRAU","section_voters":210,"latitude":null,"longitude":null,"geocoding_note":"Sem geocodificacao externa nesta etapa; latitude/longitude permanecem sem dado."}]}
