{"schema_version":"web/v1","surface":"section_results","partition":{"year":2024,"state":"RO","office_id":"11","round":1,"city_id":"744","page":1},"generated_at_utc":"2026-06-12T15:33:51.206681+00:00","source_type":"consolidado_tse","row_count":78,"rows":[{"id":"615ac88b5deb88054d21d7afdb22a753351cd46386f4871f941ccb7576bd0f64","year":2024,"round":1,"state":"RO","city_id":"744","city_name":"NOVA UNIÃO","zone_id":"28","section_id":"104","polling_place_id":"1031","polling_place_name":"ESCOLA MUNICIPAL - MARCOS ADRIANO ISSLER","office_id":"11","office":"Prefeito","candidate_id":"220001991453","candidate_number":"55","votes":128},{"id":"aa7433e3dc832b990e50b3fdfb90f84bac89e76b3f8242f23eb77168f575cd5c","year":2024,"round":1,"state":"RO","city_id":"744","city_name":"NOVA UNIÃO","zone_id":"28","section_id":"104","polling_place_id":"1031","polling_place_name":"ESCOLA MUNICIPAL - MARCOS ADRIANO ISSLER","office_id":"11","office":"Prefeito","candidate_id":"220002133946","candidate_number":"28","votes":30},{"id":"14a020a0f919d7045fb7f7fa0594ac258ab23c9704c5e1c1b91d1005df4007db","year":2024,"round":1,"state":"RO","city_id":"744","city_name":"NOVA UNIÃO","zone_id":"28","section_id":"104","polling_place_id":"1031","polling_place_name":"ESCOLA MUNICIPAL - MARCOS ADRIANO ISSLER","office_id":"11","office":"Prefeito","candidate_id":"-1","candidate_number":"96","votes":4},{"id":"14f2a626dcaf0be6028c38b97b0cd8e2cbbe86064b19d278423516550080d7f3","year":2024,"round":1,"state":"RO","city_id":"744","city_name":"NOVA UNIÃO","zone_id":"28","section_id":"113","polling_place_id":"1040","polling_place_name":"ESCOLA MUNICIPAL - MANOEL FRANCISCO DE OLIVEIRA","office_id":"11","office":"Prefeito","candidate_id":"220001991453","candidate_number":"55","votes":155},{"id":"f9b663c7a4b594283ba047c76ec56e8d1f417f7e5d5fe0825257e82a7fc07568","year":2024,"round":1,"state":"RO","city_id":"744","city_name":"NOVA UNIÃO","zone_id":"28","section_id":"113","polling_place_id":"1040","polling_place_name":"ESCOLA MUNICIPAL - MANOEL FRANCISCO DE OLIVEIRA","office_id":"11","office":"Prefeito","candidate_id":"220002133946","candidate_number":"28","votes":54},{"id":"92c897d77930d82a92a86e06619ea85eab5458235822b57d84e19efd753d6060","year":2024,"round":1,"state":"RO","city_id":"744","city_name":"NOVA UNIÃO","zone_id":"28","section_id":"113","polling_place_id":"1040","polling_place_name":"ESCOLA MUNICIPAL - MANOEL FRANCISCO DE OLIVEIRA","office_id":"11","office":"Prefeito","candidate_id":"-1","candidate_number":"95","votes":5},{"id":"83ef1303e919e40d4939eb25f4b85b8e4b73d1fc6277142d65abf746ce698b97","year":2024,"round":1,"state":"RO","city_id":"744","city_name":"NOVA UNIÃO","zone_id":"28","section_id":"113","polling_place_id":"1040","polling_place_name":"ESCOLA MUNICIPAL - MANOEL FRANCISCO DE OLIVEIRA","office_id":"11","office":"Prefeito","candidate_id":"-1","candidate_number":"96","votes":4},{"id":"37d2903c230834ea5f4f4596018789418a340e04e48a8c504dee60019b8fb9bb","year":2024,"round":1,"state":"RO","city_id":"744","city_name":"NOVA UNIÃO","zone_id":"28","section_id":"115","polling_place_id":"1040","polling_place_name":"ESCOLA MUNICIPAL - MANOEL FRANCISCO DE OLIVEIRA","office_id":"11","office":"Prefeito","candidate_id":"220001991453","candidate_number":"55","votes":172},{"id":"353f67c18460ed0513065fc1abf440725970d863260b89ab236f71a245d3b731","year":2024,"round":1,"state":"RO","city_id":"744","city_name":"NOVA UNIÃO","zone_id":"28","section_id":"115","polling_place_id":"1040","polling_place_name":"ESCOLA MUNICIPAL - MANOEL FRANCISCO DE OLIVEIRA","office_id":"11","office":"Prefeito","candidate_id":"220002133946","candidate_number":"28","votes":45},{"id":"5c05bfe62cf6321d0d4501850f408890a71e1f158387be772e7f862d069bf0ce","year":2024,"round":1,"state":"RO","city_id":"744","city_name":"NOVA UNIÃO","zone_id":"28","section_id":"115","polling_place_id":"1040","polling_place_name":"ESCOLA MUNICIPAL - MANOEL FRANCISCO DE OLIVEIRA","office_id":"11","office":"Prefeito","candidate_id":"-1","candidate_number":"96","votes":7},{"id":"5452fbfeb73db45877339adc3543cdc8c6dd31ea9e1bd37e5ec25f10a0cd9bb7","year":2024,"round":1,"state":"RO","city_id":"744","city_name":"NOVA UNIÃO","zone_id":"28","section_id":"115","polling_place_id":"1040","polling_place_name":"ESCOLA MUNICIPAL - MANOEL FRANCISCO DE OLIVEIRA","office_id":"11","office":"Prefeito","candidate_id":"-1","candidate_number":"95","votes":3},{"id":"a26f59178ff8459323641fb53b11b690e6de79f945077f8fd5d92310e0f125e6","year":2024,"round":1,"state":"RO","city_id":"744","city_name":"NOVA UNIÃO","zone_id":"28","section_id":"116","polling_place_id":"1023","polling_place_name":"ESCOLA ESTADUAL - MARIA GORETTI","office_id":"11","office":"Prefeito","candidate_id":"220001991453","candidate_number":"55","votes":135},{"id":"11321d0cf11f872d28b41c97d8a9a7ae5f57cc242693bd5437f0dd5f8d71b26e","year":2024,"round":1,"state":"RO","city_id":"744","city_name":"NOVA UNIÃO","zone_id":"28","section_id":"116","polling_place_id":"1023","polling_place_name":"ESCOLA ESTADUAL - MARIA GORETTI","office_id":"11","office":"Prefeito","candidate_id":"220002133946","candidate_number":"28","votes":36},{"id":"2253246cf21b73be898987cc1b00f1b40900522a797fde78656a594d9f89cfce","year":2024,"round":1,"state":"RO","city_id":"744","city_name":"NOVA UNIÃO","zone_id":"28","section_id":"116","polling_place_id":"1023","polling_place_name":"ESCOLA ESTADUAL - MARIA GORETTI","office_id":"11","office":"Prefeito","candidate_id":"-1","candidate_number":"96","votes":3},{"id":"c6c724cb78e166b40995f7b8c378e73f0425b6c2b8fffff4baa417fc804e7d8b","year":2024,"round":1,"state":"RO","city_id":"744","city_name":"NOVA UNIÃO","zone_id":"28","section_id":"116","polling_place_id":"1023","polling_place_name":"ESCOLA ESTADUAL - MARIA GORETTI","office_id":"11","office":"Prefeito","candidate_id":"-1","candidate_number":"95","votes":2},{"id":"cfcb057dea1f6baa61416ed3043bc1f35cb271cd3df1277dca1c1cadd9de217b","year":2024,"round":1,"state":"RO","city_id":"744","city_name":"NOVA UNIÃO","zone_id":"28","section_id":"155","polling_place_id":"1040","polling_place_name":"ESCOLA MUNICIPAL - MANOEL FRANCISCO DE OLIVEIRA","office_id":"11","office":"Prefeito","candidate_id":"220001991453","candidate_number":"55","votes":172},{"id":"bb74a40c247d1d00187cd544031e1d4e28150bcd65b884082fb6edf8a57d1387","year":2024,"round":1,"state":"RO","city_id":"744","city_name":"NOVA UNIÃO","zone_id":"28","section_id":"155","polling_place_id":"1040","polling_place_name":"ESCOLA MUNICIPAL - MANOEL FRANCISCO DE OLIVEIRA","office_id":"11","office":"Prefeito","candidate_id":"220002133946","candidate_number":"28","votes":50},{"id":"2e559201dc5b843c4c714c38815b8a46b73d6cca7b64f2e0b33a50840f10c974","year":2024,"round":1,"state":"RO","city_id":"744","city_name":"NOVA UNIÃO","zone_id":"28","section_id":"155","polling_place_id":"1040","polling_place_name":"ESCOLA MUNICIPAL - MANOEL FRANCISCO DE OLIVEIRA","office_id":"11","office":"Prefeito","candidate_id":"-1","candidate_number":"96","votes":4},{"id":"3ce8118d44907b7a61a631354467c14655fdbb433b4090ed3c76b4f4bfda679a","year":2024,"round":1,"state":"RO","city_id":"744","city_name":"NOVA UNIÃO","zone_id":"28","section_id":"156","polling_place_id":"1040","polling_place_name":"ESCOLA MUNICIPAL - MANOEL FRANCISCO DE OLIVEIRA","office_id":"11","office":"Prefeito","candidate_id":"220001991453","candidate_number":"55","votes":154},{"id":"4ebc9b5662af505a5e5e79fe524e0cd322a3ff75414e89ffcfbb3630df293477","year":2024,"round":1,"state":"RO","city_id":"744","city_name":"NOVA UNIÃO","zone_id":"28","section_id":"156","polling_place_id":"1040","polling_place_name":"ESCOLA MUNICIPAL - MANOEL FRANCISCO DE OLIVEIRA","office_id":"11","office":"Prefeito","candidate_id":"220002133946","candidate_number":"28","votes":45},{"id":"944afc0de2b2dbe33e7c67096d6ec39e0fc2ba1efe971c24bbf2f9fecb9e0dfe","year":2024,"round":1,"state":"RO","city_id":"744","city_name":"NOVA UNIÃO","zone_id":"28","section_id":"156","polling_place_id":"1040","polling_place_name":"ESCOLA MUNICIPAL - MANOEL FRANCISCO DE OLIVEIRA","office_id":"11","office":"Prefeito","candidate_id":"-1","candidate_number":"95","votes":4},{"id":"d7823753bb8fbef6b4d85291900358ef64488cd8c273878bcc7e712437e8676b","year":2024,"round":1,"state":"RO","city_id":"744","city_name":"NOVA UNIÃO","zone_id":"28","section_id":"156","polling_place_id":"1040","polling_place_name":"ESCOLA MUNICIPAL - MANOEL FRANCISCO DE OLIVEIRA","office_id":"11","office":"Prefeito","candidate_id":"-1","candidate_number":"96","votes":3},{"id":"d20b38156ff22805e1810838d278951694962af0db3bad4df68d2268e74d99d9","year":2024,"round":1,"state":"RO","city_id":"744","city_name":"NOVA UNIÃO","zone_id":"28","section_id":"157","polling_place_id":"1040","polling_place_name":"ESCOLA MUNICIPAL - MANOEL FRANCISCO DE OLIVEIRA","office_id":"11","office":"Prefeito","candidate_id":"220001991453","candidate_number":"55","votes":169},{"id":"7a9d5e2e05fcaaff81221aa2e5afdb8792b914a53e4a9bc9efd7472c1f844fd4","year":2024,"round":1,"state":"RO","city_id":"744","city_name":"NOVA UNIÃO","zone_id":"28","section_id":"157","polling_place_id":"1040","polling_place_name":"ESCOLA MUNICIPAL - MANOEL FRANCISCO DE OLIVEIRA","office_id":"11","office":"Prefeito","candidate_id":"220002133946","candidate_number":"28","votes":53},{"id":"f5389e576d6a616fc67b8c4d74caa420e1577cc46c5574bcdaa81e5519d6bacd","year":2024,"round":1,"state":"RO","city_id":"744","city_name":"NOVA UNIÃO","zone_id":"28","section_id":"157","polling_place_id":"1040","polling_place_name":"ESCOLA MUNICIPAL - MANOEL FRANCISCO DE OLIVEIRA","office_id":"11","office":"Prefeito","candidate_id":"-1","candidate_number":"96","votes":3},{"id":"ba1eb31aa3994cac8e4d720b38f7521e7197f7c955fa18fdef493d6fe734f908","year":2024,"round":1,"state":"RO","city_id":"744","city_name":"NOVA UNIÃO","zone_id":"28","section_id":"157","polling_place_id":"1040","polling_place_name":"ESCOLA MUNICIPAL - MANOEL FRANCISCO DE OLIVEIRA","office_id":"11","office":"Prefeito","candidate_id":"-1","candidate_number":"95","votes":2},{"id":"c789093bcaa5230eabab824573415b3de89340f5aa0f70f832371b630e11a6c1","year":2024,"round":1,"state":"RO","city_id":"744","city_name":"NOVA UNIÃO","zone_id":"28","section_id":"33","polling_place_id":"1023","polling_place_name":"ESCOLA ESTADUAL - MARIA GORETTI","office_id":"11","office":"Prefeito","candidate_id":"220001991453","candidate_number":"55","votes":141},{"id":"8c105274821557932725f25c18b2e447f664db11805442b22c9b55e5f8cf8cd0","year":2024,"round":1,"state":"RO","city_id":"744","city_name":"NOVA UNIÃO","zone_id":"28","section_id":"33","polling_place_id":"1023","polling_place_name":"ESCOLA ESTADUAL - MARIA GORETTI","office_id":"11","office":"Prefeito","candidate_id":"220002133946","candidate_number":"28","votes":43},{"id":"dc74f968474faf0e87afafa090ba5463d52788414a2aeedb628df2f57dced4d0","year":2024,"round":1,"state":"RO","city_id":"744","city_name":"NOVA UNIÃO","zone_id":"28","section_id":"33","polling_place_id":"1023","polling_place_name":"ESCOLA ESTADUAL - MARIA GORETTI","office_id":"11","office":"Prefeito","candidate_id":"-1","candidate_number":"96","votes":6},{"id":"d39748227580cd22496573ae40346a0e803002dbc274fff3a1d01656e479a9cf","year":2024,"round":1,"state":"RO","city_id":"744","city_name":"NOVA UNIÃO","zone_id":"28","section_id":"33","polling_place_id":"1023","polling_place_name":"ESCOLA ESTADUAL - MARIA GORETTI","office_id":"11","office":"Prefeito","candidate_id":"-1","candidate_number":"95","votes":2},{"id":"5837ce727185fc914f8585790eca5d4e0a8007848e7090e851d25c87cfaa24c3","year":2024,"round":1,"state":"RO","city_id":"744","city_name":"NOVA UNIÃO","zone_id":"28","section_id":"34","polling_place_id":"1023","polling_place_name":"ESCOLA ESTADUAL - MARIA GORETTI","office_id":"11","office":"Prefeito","candidate_id":"220001991453","candidate_number":"55","votes":161},{"id":"790c9ea6bc9d09e5a68bd431a05c5362b6b9c4e35f166e54a8ee29cb69e75038","year":2024,"round":1,"state":"RO","city_id":"744","city_name":"NOVA UNIÃO","zone_id":"28","section_id":"34","polling_place_id":"1023","polling_place_name":"ESCOLA ESTADUAL - MARIA GORETTI","office_id":"11","office":"Prefeito","candidate_id":"220002133946","candidate_number":"28","votes":34},{"id":"dfede08dd5b77ad771fee9c8d438d367e5cf1d899e94328db94d1faf10568ef9","year":2024,"round":1,"state":"RO","city_id":"744","city_name":"NOVA UNIÃO","zone_id":"28","section_id":"34","polling_place_id":"1023","polling_place_name":"ESCOLA ESTADUAL - MARIA GORETTI","office_id":"11","office":"Prefeito","candidate_id":"-1","candidate_number":"96","votes":4},{"id":"4a5d69ce5be8392bbc8ba8292b79e0740f919458248916c055008572c11f0a6d","year":2024,"round":1,"state":"RO","city_id":"744","city_name":"NOVA UNIÃO","zone_id":"28","section_id":"34","polling_place_id":"1023","polling_place_name":"ESCOLA ESTADUAL - MARIA GORETTI","office_id":"11","office":"Prefeito","candidate_id":"-1","candidate_number":"95","votes":2},{"id":"079e5b3507a2835794803f9eef90446d0c337e753a0f4de42bbd7ae41986aeda","year":2024,"round":1,"state":"RO","city_id":"744","city_name":"NOVA UNIÃO","zone_id":"28","section_id":"35","polling_place_id":"1031","polling_place_name":"ESCOLA MUNICIPAL - MARCOS ADRIANO ISSLER","office_id":"11","office":"Prefeito","candidate_id":"220001991453","candidate_number":"55","votes":236},{"id":"d41bab2190b05572ecf3adbea5b74ba74b80888dd47dc2373b5a00d581544867","year":2024,"round":1,"state":"RO","city_id":"744","city_name":"NOVA UNIÃO","zone_id":"28","section_id":"35","polling_place_id":"1031","polling_place_name":"ESCOLA MUNICIPAL - MARCOS ADRIANO ISSLER","office_id":"11","office":"Prefeito","candidate_id":"220002133946","candidate_number":"28","votes":77},{"id":"0d9425f0d797e888ea97131718913d5a3de7702d7e7b94533bcbdc854e989e88","year":2024,"round":1,"state":"RO","city_id":"744","city_name":"NOVA UNIÃO","zone_id":"28","section_id":"35","polling_place_id":"1031","polling_place_name":"ESCOLA MUNICIPAL - MARCOS ADRIANO ISSLER","office_id":"11","office":"Prefeito","candidate_id":"-1","candidate_number":"96","votes":4},{"id":"c108f925d3343e1742635517a4f584187a5b0fd0d09be70d52b8fc9607fcea6c","year":2024,"round":1,"state":"RO","city_id":"744","city_name":"NOVA UNIÃO","zone_id":"28","section_id":"35","polling_place_id":"1031","polling_place_name":"ESCOLA MUNICIPAL - MARCOS ADRIANO ISSLER","office_id":"11","office":"Prefeito","candidate_id":"-1","candidate_number":"95","votes":3},{"id":"ef68666383b0715ca713b15928dca143c7f83e52377a8271e5815ea2387e9efc","year":2024,"round":1,"state":"RO","city_id":"744","city_name":"NOVA UNIÃO","zone_id":"28","section_id":"37","polling_place_id":"1023","polling_place_name":"ESCOLA ESTADUAL - MARIA GORETTI","office_id":"11","office":"Prefeito","candidate_id":"220001991453","candidate_number":"55","votes":145},{"id":"fcba7b1c7df3da9e2705f92a2dc0dc2b12614abe889695f094ec652e2c55b019","year":2024,"round":1,"state":"RO","city_id":"744","city_name":"NOVA UNIÃO","zone_id":"28","section_id":"37","polling_place_id":"1023","polling_place_name":"ESCOLA ESTADUAL - MARIA GORETTI","office_id":"11","office":"Prefeito","candidate_id":"220002133946","candidate_number":"28","votes":43},{"id":"00c4b7c1feab16ca152aa862baa6566a977af5ed8247341be24d8859c3c099fe","year":2024,"round":1,"state":"RO","city_id":"744","city_name":"NOVA UNIÃO","zone_id":"28","section_id":"37","polling_place_id":"1023","polling_place_name":"ESCOLA ESTADUAL - MARIA GORETTI","office_id":"11","office":"Prefeito","candidate_id":"-1","candidate_number":"95","votes":3},{"id":"4dd4d5b334376d0baacab84f35eaa47acff3f04d7cca4af3c70b496e1004a789","year":2024,"round":1,"state":"RO","city_id":"744","city_name":"NOVA UNIÃO","zone_id":"28","section_id":"37","polling_place_id":"1023","polling_place_name":"ESCOLA ESTADUAL - MARIA GORETTI","office_id":"11","office":"Prefeito","candidate_id":"-1","candidate_number":"96","votes":3},{"id":"06414b53cce0fa704f5d92913e5700a20c216ac0e66a80e300d1fca002822dfd","year":2024,"round":1,"state":"RO","city_id":"744","city_name":"NOVA UNIÃO","zone_id":"28","section_id":"38","polling_place_id":"1023","polling_place_name":"ESCOLA ESTADUAL - MARIA GORETTI","office_id":"11","office":"Prefeito","candidate_id":"220001991453","candidate_number":"55","votes":150},{"id":"505bc9a3ffbd3e8b9bddf46b8ae3b6aa1b74ab0bd5e344c1c3d47a7908815ae9","year":2024,"round":1,"state":"RO","city_id":"744","city_name":"NOVA UNIÃO","zone_id":"28","section_id":"38","polling_place_id":"1023","polling_place_name":"ESCOLA ESTADUAL - MARIA GORETTI","office_id":"11","office":"Prefeito","candidate_id":"220002133946","candidate_number":"28","votes":41},{"id":"74bd03d9b6ccc6652df3e22144200d82f89a5063ceeb4f3b15e013f91d19f500","year":2024,"round":1,"state":"RO","city_id":"744","city_name":"NOVA UNIÃO","zone_id":"28","section_id":"38","polling_place_id":"1023","polling_place_name":"ESCOLA ESTADUAL - MARIA GORETTI","office_id":"11","office":"Prefeito","candidate_id":"-1","candidate_number":"96","votes":5},{"id":"33a08d76c19d3f7f2db1332104643183eb70fd3d5eaa4dd0f60734348a932eed","year":2024,"round":1,"state":"RO","city_id":"744","city_name":"NOVA UNIÃO","zone_id":"28","section_id":"38","polling_place_id":"1023","polling_place_name":"ESCOLA ESTADUAL - MARIA GORETTI","office_id":"11","office":"Prefeito","candidate_id":"-1","candidate_number":"95","votes":1},{"id":"369424f1abf839f607e5ad7a2eafd9b14902c24320679416ad7d272c5fcdf807","year":2024,"round":1,"state":"RO","city_id":"744","city_name":"NOVA UNIÃO","zone_id":"28","section_id":"39","polling_place_id":"1023","polling_place_name":"ESCOLA ESTADUAL - MARIA GORETTI","office_id":"11","office":"Prefeito","candidate_id":"220001991453","candidate_number":"55","votes":149},{"id":"86422c736fd73eb0f1b599ba6cf07564ac341bc98c681f1b5cdef55e21af7256","year":2024,"round":1,"state":"RO","city_id":"744","city_name":"NOVA UNIÃO","zone_id":"28","section_id":"39","polling_place_id":"1023","polling_place_name":"ESCOLA ESTADUAL - MARIA GORETTI","office_id":"11","office":"Prefeito","candidate_id":"220002133946","candidate_number":"28","votes":37},{"id":"5c57fc653a0a173ee7b9978070587bd4f1414991a4a9892c4bca8910798fa118","year":2024,"round":1,"state":"RO","city_id":"744","city_name":"NOVA UNIÃO","zone_id":"28","section_id":"39","polling_place_id":"1023","polling_place_name":"ESCOLA ESTADUAL - MARIA GORETTI","office_id":"11","office":"Prefeito","candidate_id":"-1","candidate_number":"96","votes":7},{"id":"92f740877f8612f5780cc1643246956c1d1adc49c942776b7df7abecf551acaf","year":2024,"round":1,"state":"RO","city_id":"744","city_name":"NOVA UNIÃO","zone_id":"28","section_id":"39","polling_place_id":"1023","polling_place_name":"ESCOLA ESTADUAL - MARIA GORETTI","office_id":"11","office":"Prefeito","candidate_id":"-1","candidate_number":"95","votes":4},{"id":"caf69d25f4017848c6cd290a597b65ec9e4bef391cdfd25f6aad417c0e15da11","year":2024,"round":1,"state":"RO","city_id":"744","city_name":"NOVA UNIÃO","zone_id":"28","section_id":"40","polling_place_id":"1023","polling_place_name":"ESCOLA ESTADUAL - MARIA GORETTI","office_id":"11","office":"Prefeito","candidate_id":"220001991453","candidate_number":"55","votes":158},{"id":"9b03b6412caa4c3e5a6db6bc232dd298eb7cac140154899bb0feae7fef89469a","year":2024,"round":1,"state":"RO","city_id":"744","city_name":"NOVA UNIÃO","zone_id":"28","section_id":"40","polling_place_id":"1023","polling_place_name":"ESCOLA ESTADUAL - MARIA GORETTI","office_id":"11","office":"Prefeito","candidate_id":"220002133946","candidate_number":"28","votes":37},{"id":"33faefb385e06356ce6de243a9cc81b6addefa7094f69006558e6a1c2cc93247","year":2024,"round":1,"state":"RO","city_id":"744","city_name":"NOVA UNIÃO","zone_id":"28","section_id":"40","polling_place_id":"1023","polling_place_name":"ESCOLA ESTADUAL - MARIA GORETTI","office_id":"11","office":"Prefeito","candidate_id":"-1","candidate_number":"95","votes":5},{"id":"a9661255fb5eada442bfa9824987d245391368bf15ffcaa83e1fa61fed81362e","year":2024,"round":1,"state":"RO","city_id":"744","city_name":"NOVA UNIÃO","zone_id":"28","section_id":"40","polling_place_id":"1023","polling_place_name":"ESCOLA ESTADUAL - MARIA GORETTI","office_id":"11","office":"Prefeito","candidate_id":"-1","candidate_number":"96","votes":2},{"id":"fd1a22e788c3df8a81855a3a481ce45e6e4f7047db0ba68e332a80873d6247ad","year":2024,"round":1,"state":"RO","city_id":"744","city_name":"NOVA UNIÃO","zone_id":"28","section_id":"41","polling_place_id":"1023","polling_place_name":"ESCOLA ESTADUAL - MARIA GORETTI","office_id":"11","office":"Prefeito","candidate_id":"220001991453","candidate_number":"55","votes":145},{"id":"f6aa959df3d55f2b7361b240fcef06ff2156bbd995a305eb38c5ae601bdf81e2","year":2024,"round":1,"state":"RO","city_id":"744","city_name":"NOVA UNIÃO","zone_id":"28","section_id":"41","polling_place_id":"1023","polling_place_name":"ESCOLA ESTADUAL - MARIA GORETTI","office_id":"11","office":"Prefeito","candidate_id":"220002133946","candidate_number":"28","votes":42},{"id":"7b0065f4bdbf8a5f9b7b9933752e3c8b144cb1263e482e77b5a02075c122b660","year":2024,"round":1,"state":"RO","city_id":"744","city_name":"NOVA UNIÃO","zone_id":"28","section_id":"41","polling_place_id":"1023","polling_place_name":"ESCOLA ESTADUAL - MARIA GORETTI","office_id":"11","office":"Prefeito","candidate_id":"-1","candidate_number":"96","votes":6},{"id":"910bdc98898ab425555a3b8639175ef4533cc952673cf11d91d6a7f357d259d4","year":2024,"round":1,"state":"RO","city_id":"744","city_name":"NOVA UNIÃO","zone_id":"28","section_id":"41","polling_place_id":"1023","polling_place_name":"ESCOLA ESTADUAL - MARIA GORETTI","office_id":"11","office":"Prefeito","candidate_id":"-1","candidate_number":"95","votes":3},{"id":"4e3f5357853806a0c4901975737c4c7d5ed3ff7a75bfb849ce43cd3997f8f1bf","year":2024,"round":1,"state":"RO","city_id":"744","city_name":"NOVA UNIÃO","zone_id":"28","section_id":"42","polling_place_id":"1023","polling_place_name":"ESCOLA ESTADUAL - MARIA GORETTI","office_id":"11","office":"Prefeito","candidate_id":"220001991453","candidate_number":"55","votes":146},{"id":"0ee7bbec1c52342a7630aef9ec51268c10220169a9b9ea6e5c580421546a4a7b","year":2024,"round":1,"state":"RO","city_id":"744","city_name":"NOVA UNIÃO","zone_id":"28","section_id":"42","polling_place_id":"1023","polling_place_name":"ESCOLA ESTADUAL - MARIA GORETTI","office_id":"11","office":"Prefeito","candidate_id":"220002133946","candidate_number":"28","votes":47},{"id":"409214f23b4c38c219be59fd4178461953d3717c2dec52e2c7a5b153887d0b6b","year":2024,"round":1,"state":"RO","city_id":"744","city_name":"NOVA UNIÃO","zone_id":"28","section_id":"42","polling_place_id":"1023","polling_place_name":"ESCOLA ESTADUAL - MARIA GORETTI","office_id":"11","office":"Prefeito","candidate_id":"-1","candidate_number":"96","votes":5},{"id":"265a578c00b41d838e3f117e311885c08c5da81ad7ab614823078e3b9d8810d7","year":2024,"round":1,"state":"RO","city_id":"744","city_name":"NOVA UNIÃO","zone_id":"28","section_id":"42","polling_place_id":"1023","polling_place_name":"ESCOLA ESTADUAL - MARIA GORETTI","office_id":"11","office":"Prefeito","candidate_id":"-1","candidate_number":"95","votes":3},{"id":"a963e6012734a784f85c37a209cf83da5402711d59123d2b8942b354d78a79e3","year":2024,"round":1,"state":"RO","city_id":"744","city_name":"NOVA UNIÃO","zone_id":"28","section_id":"43","polling_place_id":"1023","polling_place_name":"ESCOLA ESTADUAL - MARIA GORETTI","office_id":"11","office":"Prefeito","candidate_id":"220001991453","candidate_number":"55","votes":137},{"id":"0e442e02ee167310714ba44c783ac53c7fefab6d05cd4c9ca7fb6b7398199f75","year":2024,"round":1,"state":"RO","city_id":"744","city_name":"NOVA UNIÃO","zone_id":"28","section_id":"43","polling_place_id":"1023","polling_place_name":"ESCOLA ESTADUAL - MARIA GORETTI","office_id":"11","office":"Prefeito","candidate_id":"220002133946","candidate_number":"28","votes":42},{"id":"1548b83297fd17953c2942fea8a7bc612b97f63726a53ba534e3ac03ad3c4614","year":2024,"round":1,"state":"RO","city_id":"744","city_name":"NOVA UNIÃO","zone_id":"28","section_id":"43","polling_place_id":"1023","polling_place_name":"ESCOLA ESTADUAL - MARIA GORETTI","office_id":"11","office":"Prefeito","candidate_id":"-1","candidate_number":"96","votes":7},{"id":"6dc7950da20bfa7b398cdc4afea7b84177f6ee43c53b512f7c2cdb8bc781e6ab","year":2024,"round":1,"state":"RO","city_id":"744","city_name":"NOVA UNIÃO","zone_id":"28","section_id":"43","polling_place_id":"1023","polling_place_name":"ESCOLA ESTADUAL - MARIA GORETTI","office_id":"11","office":"Prefeito","candidate_id":"-1","candidate_number":"95","votes":2},{"id":"1f71043713d07fb4c6de0e3e4439a1fe40544addf1747e19381c0565866a612c","year":2024,"round":1,"state":"RO","city_id":"744","city_name":"NOVA UNIÃO","zone_id":"28","section_id":"63","polling_place_id":"1031","polling_place_name":"ESCOLA MUNICIPAL - MARCOS ADRIANO ISSLER","office_id":"11","office":"Prefeito","candidate_id":"220001991453","candidate_number":"55","votes":240},{"id":"5109c50f1d8ad2e2137e849607dfd2c3e95696b361d9c2af80845dd334406e5a","year":2024,"round":1,"state":"RO","city_id":"744","city_name":"NOVA UNIÃO","zone_id":"28","section_id":"63","polling_place_id":"1031","polling_place_name":"ESCOLA MUNICIPAL - MARCOS ADRIANO ISSLER","office_id":"11","office":"Prefeito","candidate_id":"220002133946","candidate_number":"28","votes":77},{"id":"050faeb7b8ce7abc4787505ebf7b7de8d1706f8c875c4c58f028c2799959455a","year":2024,"round":1,"state":"RO","city_id":"744","city_name":"NOVA UNIÃO","zone_id":"28","section_id":"63","polling_place_id":"1031","polling_place_name":"ESCOLA MUNICIPAL - MARCOS ADRIANO ISSLER","office_id":"11","office":"Prefeito","candidate_id":"-1","candidate_number":"96","votes":5},{"id":"4750a52ffa68215868c81e652b8a2047f4801f7c67de33267b067c6412253980","year":2024,"round":1,"state":"RO","city_id":"744","city_name":"NOVA UNIÃO","zone_id":"28","section_id":"63","polling_place_id":"1031","polling_place_name":"ESCOLA MUNICIPAL - MARCOS ADRIANO ISSLER","office_id":"11","office":"Prefeito","candidate_id":"-1","candidate_number":"95","votes":5},{"id":"f22a9388c302c4be47246ae77b638898c0a5dc475d657d07ad56dbf4c61cbb1c","year":2024,"round":1,"state":"RO","city_id":"744","city_name":"NOVA UNIÃO","zone_id":"28","section_id":"64","polling_place_id":"1023","polling_place_name":"ESCOLA ESTADUAL - MARIA GORETTI","office_id":"11","office":"Prefeito","candidate_id":"220001991453","candidate_number":"55","votes":141},{"id":"78bad69d09434885dc3eba4578dc1e839f1383de25336b87885b8f39cfce467c","year":2024,"round":1,"state":"RO","city_id":"744","city_name":"NOVA UNIÃO","zone_id":"28","section_id":"64","polling_place_id":"1023","polling_place_name":"ESCOLA ESTADUAL - MARIA GORETTI","office_id":"11","office":"Prefeito","candidate_id":"220002133946","candidate_number":"28","votes":47},{"id":"672aba58ccfd185e8d59c0a30fe85255895f7589876a8c88367bf3d75afcfb80","year":2024,"round":1,"state":"RO","city_id":"744","city_name":"NOVA UNIÃO","zone_id":"28","section_id":"64","polling_place_id":"1023","polling_place_name":"ESCOLA ESTADUAL - MARIA GORETTI","office_id":"11","office":"Prefeito","candidate_id":"-1","candidate_number":"95","votes":4},{"id":"c95dccecf531582f294b45806b6d774f35e364ab1742a0af9af0ac2f3c3ea9fa","year":2024,"round":1,"state":"RO","city_id":"744","city_name":"NOVA UNIÃO","zone_id":"28","section_id":"64","polling_place_id":"1023","polling_place_name":"ESCOLA ESTADUAL - MARIA GORETTI","office_id":"11","office":"Prefeito","candidate_id":"-1","candidate_number":"96","votes":3},{"id":"d1373c745d93bf520fe3b2a3ae11f67daddbead7174d18820e57a6907b1c77a4","year":2024,"round":1,"state":"RO","city_id":"744","city_name":"NOVA UNIÃO","zone_id":"28","section_id":"93","polling_place_id":"1031","polling_place_name":"ESCOLA MUNICIPAL - MARCOS ADRIANO ISSLER","office_id":"11","office":"Prefeito","candidate_id":"220001991453","candidate_number":"55","votes":241},{"id":"0c258ea0fdb824ec65cff6719800ee019b93e2a6b6b945e057bd7087e2b710b3","year":2024,"round":1,"state":"RO","city_id":"744","city_name":"NOVA UNIÃO","zone_id":"28","section_id":"93","polling_place_id":"1031","polling_place_name":"ESCOLA MUNICIPAL - MARCOS ADRIANO ISSLER","office_id":"11","office":"Prefeito","candidate_id":"220002133946","candidate_number":"28","votes":73},{"id":"ab7bbd272a90f205e605d3779a9a21e132891aa121a561fb5d7a11e7afe800c5","year":2024,"round":1,"state":"RO","city_id":"744","city_name":"NOVA UNIÃO","zone_id":"28","section_id":"93","polling_place_id":"1031","polling_place_name":"ESCOLA MUNICIPAL - MARCOS ADRIANO ISSLER","office_id":"11","office":"Prefeito","candidate_id":"-1","candidate_number":"96","votes":6},{"id":"c5dac4bf338c3c9a9b830e8d391733430d9be0ae8ee8f4207f0c004de225e2dd","year":2024,"round":1,"state":"RO","city_id":"744","city_name":"NOVA UNIÃO","zone_id":"28","section_id":"93","polling_place_id":"1031","polling_place_name":"ESCOLA MUNICIPAL - MARCOS ADRIANO ISSLER","office_id":"11","office":"Prefeito","candidate_id":"-1","candidate_number":"95","votes":4}]}
