{"schema_version":"web/v1","surface":"section_turnout","partition":{"year":2024,"state":"RO","round":1,"city_id":"00418","page":1},"generated_at_utc":"2026-06-12T15:33:51.206681+00:00","source_type":"consolidado_tse_partial","row_count":1,"rows":[{"id":"a5ae1d085a6760f370fbbf042dc4383c4b28831344a0bf579ca057415edcb084","year":2024,"round":1,"state":"RO","city_id":"00418","city_name":"SÃO MIGUEL DO GUAPORÉ","zone_id":"35","section_id":null,"eligible_voters":34104,"turnout":27044,"abstention":7060,"turnout_rate":0.7929861599812339,"abstention_rate":0.20701384001876613,"coverage_note":"Cobertura por zona/perfil agregada; comparecimento por secao nao esta materializado nesta fonte."}]}
